calfram/__init__.py
calfram/calibrationframework.py
calfram/ece.py
calibrationframework-0.1.1.dist-info/LICENSE
calibrationframework-0.1.1.dist-info/METADATA
calibrationframework-0.1.1.dist-info/WHEEL
calibrationframework-0.1.1.dist-info/top_level.txt
calibrationframework-0.1.1.dist-info/RECORD
