Metadata-Version: 2.1
Name: calibrationframework
Version: 0.1.1
Summary: A comprehensive framework for assessing calibration in machine and deep learning models
Home-page: https://github.com/lorenzofamiglini/CalFram
Author: Lorenzo Famiglini
Author-email: lorenzofamiglini@gmail.com
License-File: LICENSE
Requires-Dist: pandas
Requires-Dist: numpy
Requires-Dist: matplotlib
Requires-Dist: scikit-learn
Requires-Dist: ipdb
